__init__.py
Model/__init__.py
Model/Binomial/BinomialOptionPrice.py
Model/Binomial/__init__.py
Option/Option.py
Option/__init__.py
ZoroOptions-0.0.1.dist-info/METADATA
ZoroOptions-0.0.1.dist-info/WHEEL
ZoroOptions-0.0.1.dist-info/top_level.txt
ZoroOptions-0.0.1.dist-info/RECORD
