Metadata-Version: 2.1
Name: ZoroOptions
Version: 0.0.1
Summary: First version for ZoroOptions
Author-email: Bharat Swami <bharatswami1299@gmail.com>
Classifier: Programming Language :: Python :: 3
Classifier: License :: OSI Approved :: MIT License
Classifier: Operating System :: OS Independent
Requires-Python: >=3.8
